embedding_flow/__init__.py
embedding_flow/main.py
embedding_flow/contracts/__init__.py
embedding_flow/contracts/contracts.py
embedding_flow/load/__init__.py
embedding_flow/load/load.py
embedding_flow/transform/__init__.py
embedding_flow/transform/transform.py
embedding_flow-0.1.9.dist-info/licenses/LICENSE
embedding_flow-0.1.9.dist-info/METADATA
embedding_flow-0.1.9.dist-info/WHEEL
embedding_flow-0.1.9.dist-info/top_level.txt
embedding_flow-0.1.9.dist-info/RECORD
