Metadata-Version: 2.4
Name: embedding-flow
Version: 0.1.9
Summary: Pipeline to transform text chunks into embeddings and load to Qdrant
Author: facuvega
Classifier: Programming Language :: Python :: 3
Classifier: Programming Language :: Python :: 3.10
Classifier: Programming Language :: Python :: 3.11
Classifier: Programming Language :: Python :: 3.12
Classifier: License :: OSI Approved :: MIT License
Classifier: Operating System :: OS Independent
Requires-Python: >=3.10
License-File: LICENSE
Requires-Dist: torch==2.3.1
Requires-Dist: sentence-transformers>=2.2.0
Requires-Dist: transformers>=4.30.0
Requires-Dist: pandas
Requires-Dist: pyarrow
Requires-Dist: qdrant-client>=1.7.0
Requires-Dist: python-dotenv
Provides-Extra: dev
Requires-Dist: pytest>=7.0.0; extra == "dev"
Requires-Dist: pytest-cov>=4.0.0; extra == "dev"
Provides-Extra: cpu
Requires-Dist: torch>=2.0.0; extra == "cpu"
Provides-Extra: cuda
Requires-Dist: torch>=2.0.0; extra == "cuda"
Dynamic: license-file
